asynccachetools/__init__.py
asynccachetools-0.1.9.dist-info/METADATA
asynccachetools-0.1.9.dist-info/WHEEL
asynccachetools-0.1.9.dist-info/RECORD
